{
    "id": "starship",
    "name": "Starship Prompt",
    "version": "1.2.0",
    "description": "A fast, customizable cross-shell prompt with contextual information display.",
    "documentationURL": "https://github.com/devcontainers-features/tools/tree/main/src/starship",
    "options": {
        "version": {
            "description": "Select the version to install.",
            "type": "string",
            "proposals": [
                "latest"
            ],
            "default": "latest"
        }
    },
    "installsAfter": [
        "ghcr.io/devcontainers/features/common-utils"
    ]
}
